{
  "aggiornato": "2026-03-25T09:36:58Z",
  "aggiornato_it": "25/03/2026 09:36",
  "fondi": [
    {
      "nome": "Lux Im Intermonte PIR Ita SmallMid",
      "isin": "LU1698605562",
      "navAtt": 140.142,
      "errore": false
    },
    {
      "nome": "Lux Im Goldman Sachs Global Eq Op",
      "isin": "LU1881760893",
      "navAtt": 174.819,
      "errore": false
    },
    {
      "nome": "Lux Im Blackrock Credit Defensive St",
      "isin": "LU0894903326",
      "navAtt": 103.472,
      "errore": true
    },
    {
      "nome": "Ff World Fund E Acc Euro",
      "isin": "LU0115769746",
      "navAtt": 52.34,
      "errore": false
    },
    {
      "nome": "Eurizon Az.Internaz.Etico",
      "isin": "IT0001083424",
      "navAtt": 21.57,
      "errore": false
    }
  ],
  "errori": [
    "Lux Im Blackrock Credit Defensive St"
  ]
}